{
	"players": [],
	"categories": [
		{
			"name": "Example Category",
			"items": [
				{
					"name": "Example Item 1",
					"id": 2
				},
				{
					"name": "Example Item 2",
					"id": 3
				},
				{
					"name": "Example Item 3",
					"id": 4
				},
				{
					"name": "Example Item 4",
					"id": 5
				},
				{
					"name": "Example Item 5",
					"id": 6
				},
				{
					"name": "Example Item 6",
					"id": 7
				},
				{
					"name": "Example Item 7",
					"id": 8
				},
				{
					"name": "Example Item 8",
					"id": 9
				},
				{
					"name": "Example Item 9",
					"id": 10
				}
			],
			"id": 1
		}
	],
	"currentVote": false,
	"voteQueue": []
}